kax/__init__.py
kax/acts.py
kax/fsOperations.py
kax/mem.py
kax/pub.py
kax/sub.py
kax-0.1.4.dist-info/LICENSE
kax-0.1.4.dist-info/METADATA
kax-0.1.4.dist-info/WHEEL
kax-0.1.4.dist-info/RECORD
